odoo9_addon_mis_builder_demo-9.0.3.1.0-nspkg.pth
odoo_addons/mis_builder_demo/README.rst
odoo_addons/mis_builder_demo/__init__.py
odoo_addons/mis_builder_demo/__openerp__.py
odoo_addons/mis_builder_demo/data/mis_budget.xml
odoo_addons/mis_builder_demo/data/mis_report.xml
odoo_addons/mis_builder_demo/data/mis_report_instance.xml
odoo_addons/mis_builder_demo/data/mis_report_style.xml
odoo_addons/mis_builder_demo/i18n/ca.po
odoo_addons/mis_builder_demo/i18n/de.po
odoo_addons/mis_builder_demo/i18n/es.po
odoo_addons/mis_builder_demo/i18n/fr.po
odoo_addons/mis_builder_demo/i18n/mis_builder_demo.pot
odoo_addons/mis_builder_demo/i18n/nl.po
odoo_addons/mis_builder_demo/i18n/nl_NL.po
odoo_addons/mis_builder_demo/i18n/pt.po
odoo_addons/mis_builder_demo/models/__init__.py
odoo_addons/mis_builder_demo/models/mis_committed_purchase.py
odoo_addons/mis_builder_demo/models/mis_committed_purchase.sql
odoo_addons/mis_builder_demo/readme/CONTRIBUTORS.rst
odoo_addons/mis_builder_demo/readme/DESCRIPTION.rst
odoo_addons/mis_builder_demo/readme/HISTORY.rst
odoo_addons/mis_builder_demo/readme/ROADMAP.rst
odoo_addons/mis_builder_demo/readme/USAGE.rst
odoo_addons/mis_builder_demo/readme/newsfragments/.gitignore
odoo_addons/mis_builder_demo/security/mis_committed_purchase.xml
odoo_addons/mis_builder_demo/static/description/icon.png
odoo_addons/mis_builder_demo/static/description/index.html
odoo_addons/mis_builder_demo/views/mis_committed_purchase.xml
odoo9_addon_mis_builder_demo-9.0.3.1.0.dist-info/METADATA
odoo9_addon_mis_builder_demo-9.0.3.1.0.dist-info/WHEEL
odoo9_addon_mis_builder_demo-9.0.3.1.0.dist-info/namespace_packages.txt
odoo9_addon_mis_builder_demo-9.0.3.1.0.dist-info/top_level.txt
odoo9_addon_mis_builder_demo-9.0.3.1.0.dist-info/RECORD
